prodius/__init__.py
prodius/_product.py
prodius/exceptions.py
prodius-0.0.3.dist-info/LICENSE
prodius-0.0.3.dist-info/METADATA
prodius-0.0.3.dist-info/WHEEL
prodius-0.0.3.dist-info/top_level.txt
prodius-0.0.3.dist-info/RECORD
